dataclass_flex/__init__.py
dataclass_flex/dataclass_flex.py
dataclass_flex/utils.py
dataclass_flex-0.0.1.dist-info/LICENSE
dataclass_flex-0.0.1.dist-info/METADATA
dataclass_flex-0.0.1.dist-info/WHEEL
dataclass_flex-0.0.1.dist-info/top_level.txt
dataclass_flex-0.0.1.dist-info/RECORD
